isitpangram/__init__.py
isitpangram/cli.py
isitpangram/isitpangram.py
isitpangram-0.4.0.dist-info/DESCRIPTION.rst
isitpangram-0.4.0.dist-info/METADATA
isitpangram-0.4.0.dist-info/RECORD
isitpangram-0.4.0.dist-info/WHEEL
isitpangram-0.4.0.dist-info/entry_points.txt
isitpangram-0.4.0.dist-info/metadata.json
isitpangram-0.4.0.dist-info/top_level.txt
