Metadata-Version: 2.0
Name: isitpangram
Version: 0.4.0
Summary: A function to determine if a sentence is a pangram.
Home-page: https://github.com/fertek/isitpangram
Author: Jan Feřtek
Author-email: janfertek@gmail.com
License: MIT license
Keywords: isitpangram
Platform: UNKNOWN
Classifier: Development Status :: 2 - Pre-Alpha
Classifier: Intended Audience :: Developers
Classifier: License :: OSI Approved :: MIT License
Classifier: Natural Language :: English
Classifier: Programming Language :: Python :: 2
Classifier: Programming Language :: Python :: 2.7
Classifier: Programming Language :: Python :: 3
Classifier: Programming Language :: Python :: 3.4
Classifier: Programming Language :: Python :: 3.5
Classifier: Programming Language :: Python :: 3.6
Requires-Dist: Click (>=6.0)
